{
    "_default": {
        "6": {
            "first_name": "Georges",
            "last_name": "Simon",
            "phone_number": "0123456789",
            "address": "30, boulevard Leroy\n25726 BuissonBourg"
        },
        "7": {
            "first_name": "Margaux",
            "last_name": "Bouchet",
            "phone_number": "0123456789",
            "address": "98, avenue Alain Gros\n16905 Leroy-la-For\u00eat"
        },
        "8": {
            "first_name": "Alexandrie",
            "last_name": "Duhamel",
            "phone_number": "0123456789",
            "address": "40, rue Arthur Brunel\n33827 Sauvage-sur-Sanchez"
        },
        "9": {
            "first_name": "Sabine",
            "last_name": "Mend\u00e8s",
            "phone_number": "0123456789",
            "address": "1, rue Gros\n88896 Sainte Paul"
        },
        "10": {
            "first_name": "Mich\u00e8le",
            "last_name": "Mallet",
            "phone_number": "0123456789",
            "address": "23, rue Robert Lemonnier\n53456 Leclerc"
        },
        "11": {
            "first_name": "Chantal",
            "last_name": "Bourdon",
            "phone_number": "+33 (0)1 70 57 32 29",
            "address": "78, avenue Cl\u00e9mence Mar\u00e9chal\n18174 Guichard"
        },
        "12": {
            "first_name": "Margaux",
            "last_name": "Leroy",
            "phone_number": "+33 1 82 86 85 29",
            "address": "22, avenue de Pons\n57677 Saint Guy-les-Bains"
        },
        "13": {
            "first_name": "Paul",
            "last_name": "Herv\u00e9",
            "phone_number": "06 16 23 82 85",
            "address": "rue Rodriguez\n35696 Riou"
        },
        "14": {
            "first_name": "Jeannine",
            "last_name": "Lombard",
            "phone_number": "+33 (0)6 36 56 77 07",
            "address": "901, rue de Dijoux\n72454 Sainte Fran\u00e7oise-les-Bains"
        },
        "15": {
            "first_name": "Guy",
            "last_name": "Labb\u00e9",
            "phone_number": "0426795962",
            "address": "7, rue de Lacroix\n56541 Leduc-sur-Blondel"
        },
        "16": {
            "first_name": "\u00c9douard",
            "last_name": "Vidal",
            "phone_number": "+33 2 53 56 51 13",
            "address": "25, avenue Sophie Costa\n60206 Bruneau"
        },
        "17": {
            "first_name": "Chantal",
            "last_name": "Breton",
            "phone_number": "+33 3 62 48 31 01",
            "address": "667, rue Maillot\n22293 Saint Patrick"
        },
        "18": {
            "first_name": "Arthur",
            "last_name": "Brunet",
            "phone_number": "04 44 77 56 46",
            "address": "rue Fabre\n91257 Dupuy-les-Bains"
        },
        "19": {
            "first_name": "Jos\u00e9phine",
            "last_name": "Lagarde",
            "phone_number": "+33 (0)4 27 77 00 80",
            "address": "177, boulevard de Boutin\n93299 Guyon"
        },
        "20": {
            "first_name": "Louis",
            "last_name": "Martin",
            "phone_number": "+33 7 58 77 62 53",
            "address": "67, rue Paris\n23256 Benard"
        },
        "21": {
            "first_name": "Marianne",
            "last_name": "Jacob",
            "phone_number": "02 45 17 18 77",
            "address": "60, chemin Pereira\n31782 Gomes"
        },
        "22": {
            "first_name": "Fr\u00e9d\u00e9ric",
            "last_name": "Pinto",
            "phone_number": "03 84 48 57 02",
            "address": "9, boulevard Patricia Rey\n83918 Saint Claudine"
        },
        "25": {
            "first_name": "Fr\u00e9d\u00e9ric",
            "last_name": "Albert",
            "phone_number": "+33 1 80 24 71 53",
            "address": "46, rue de Monnier\n80241 Blondel"
        },
        "26": {
            "first_name": "Juliette",
            "last_name": "Briand",
            "phone_number": "+33 (0)2 29 06 78 92",
            "address": "avenue de Aubert\n71270 Jacquet"
        },
        "27": {
            "first_name": "Gabriel",
            "last_name": "Leclerc",
            "phone_number": "03 80 40 79 78",
            "address": "57, chemin Hardy\n97220 MaheBourg"
        },
        "28": {
            "first_name": "Charlotte",
            "last_name": "Rodriguez",
            "phone_number": "03 60 35 29 85",
            "address": "409, rue de Toussaint\n69535 LaporteVille"
        },
        "29": {
            "first_name": "Diane",
            "last_name": "Rodrigues",
            "phone_number": "03 60 26 25 00",
            "address": "97, rue de Potier\n34342 Lefort-sur-Monnier"
        },
        "30": {
            "first_name": "Lucie",
            "last_name": "Huet",
            "phone_number": "0364198418",
            "address": "chemin Robert Baron\n87708 Saint Marianneboeuf"
        }
    }
}